[
    {
        "time_step": 124,
        "datacenter_id": "DC4",
        "server_generation": "CPU.S4",
        "server_id": 1,
        "action": "buy",
        "quantity": 508
    },
    {
        "time_step": 127,
        "datacenter_id": "DC2",
        "server_generation": "GPU.S3",
        "server_id": 2,
        "action": "buy",
        "quantity": 451
    },
    {
        "time_step": 79,
        "datacenter_id": "DC4",
        "server_generation": "GPU.S2",
        "server_id": 5,
        "action": "buy",
        "quantity": 7
    },
    {
        "time_step": 80,
        "datacenter_id": "DC2",
        "server_generation": "CPU.S2",
        "server_id": 9,
        "action": "buy",
        "quantity": 903
    },
    {
        "time_step": 14,
        "datacenter_id": "DC1",
        "server_generation": "CPU.S1",
        "server_id": 10,
        "action": "buy",
        "quantity": 775
    },
    {
        "time_step": 46,
        "datacenter_id": "DC3",
        "server_generation": "CPU.S2",
        "server_id": 11,
        "action": "buy",
        "quantity": 732
    },
    {
        "time_step": 114,
        "datacenter_id": "DC2",
        "server_generation": "GPU.S2",
        "server_id": 12,
        "action": "buy",
        "quantity": 382
    },
    {
        "time_step": 128,
        "datacenter_id": "DC4",
        "server_generation": "CPU.S4",
        "server_id": 17,
        "action": "buy",
        "quantity": 294
    },
    {
        "time_step": 13,
        "datacenter_id": "DC4",
        "server_generation": "GPU.S1",
        "server_id": 18,
        "action": "buy",
        "quantity": 400
    },
    {
        "time_step": 154,
        "datacenter_id": "DC3",
        "server_generation": "GPU.S3",
        "server_id": 20,
        "action": "buy",
        "quantity": 370
    },
    {
        "time_step": 28,
        "datacenter_id": "DC3",
        "server_generation": "GPU.S1",
        "server_id": 21,
        "action": "buy",
        "quantity": 190
    },
    {
        "time_step": 153,
        "datacenter_id": "DC4",
        "server_generation": "GPU.S3",
        "server_id": 22,
        "action": "buy",
        "quantity": 46
    },
    {
        "time_step": 39,
        "datacenter_id": "DC2",
        "server_generation": "GPU.S1",
        "server_id": 25,
        "action": "buy",
        "quantity": 311
    },
    {
        "time_step": 116,
        "datacenter_id": "DC1",
        "server_generation": "CPU.S3",
        "server_id": 27,
        "action": "buy",
        "quantity": 188
    },
    {
        "time_step": 93,
        "datacenter_id": "DC2",
        "server_generation": "CPU.S2",
        "server_id": 28,
        "action": "buy",
        "quantity": 153
    },
    {
        "time_step": 124,
        "datacenter_id": "DC3",
        "server_generation": "CPU.S3",
        "server_id": 29,
        "action": "buy",
        "quantity": 183
    },
    {
        "time_step": 96,
        "datacenter_id": "DC2",
        "server_generation": "CPU.S2",
        "server_id": 32,
        "action": "buy",
        "quantity": 119
    },
    {
        "time_step": 110,
        "datacenter_id": "DC3",
        "server_generation": "CPU.S3",
        "server_id": 36,
        "action": "buy",
        "quantity": 385
    },
    {
        "time_step": 114,
        "datacenter_id": "DC4",
        "server_generation": "GPU.S3",
        "server_id": 37,
        "action": "buy",
        "quantity": 276
    },
    {
        "time_step": 142,
        "datacenter_id": "DC3",
        "server_generation": "CPU.S4",
        "server_id": 38,
        "action": "buy",
        "quantity": 30
    },
    {
        "time_step": 11,
        "datacenter_id": "DC1",
        "server_generation": "CPU.S1",
        "server_id": 39,
        "action": "buy",
        "quantity": 1496
    },
    {
        "time_step": 97,
        "datacenter_id": "DC2",
        "server_generation": "CPU.S3",
        "server_id": 40,
        "action": "buy",
        "quantity": 699
    },
    {
        "time_step": 16,
        "datacenter_id": "DC4",
        "server_generation": "CPU.S1",
        "server_id": 42,
        "action": "buy",
        "quantity": 698
    },
    {
        "time_step": 110,
        "datacenter_id": "DC1",
        "server_generation": "CPU.S3",
        "server_id": 43,
        "action": "buy",
        "quantity": 760
    },
    {
        "time_step": 140,
        "datacenter_id": "DC4",
        "server_generation": "GPU.S3",
        "server_id": 44,
        "action": "buy",
        "quantity": 289
    },
    {
        "time_step": 11,
        "datacenter_id": "DC3",
        "server_generation": "GPU.S1",
        "server_id": 46,
        "action": "buy",
        "quantity": 40
    },
    {
        "time_step": 9,
        "datacenter_id": "DC1",
        "server_generation": "CPU.S1",
        "server_id": 50,
        "action": "buy",
        "quantity": 170
    }
]