[
    {
        "time_step": 110,
        "datacenter_id": "DC4",
        "server_generation": "CPU.S4",
        "server_id": "1",
        "action": "buy",
        "quantity": 371
    },
    {
        "time_step": 9,
        "datacenter_id": "DC4",
        "server_generation": "CPU.S1",
        "server_id": "3",
        "action": "buy",
        "quantity": 262
    },
    {
        "time_step": 162,
        "datacenter_id": "DC3",
        "server_generation": "CPU.S4",
        "server_id": "5",
        "action": "buy",
        "quantity": 49
    },
    {
        "time_step": 12,
        "datacenter_id": "DC1",
        "server_generation": "GPU.S1",
        "server_id": "6",
        "action": "buy",
        "quantity": 285
    },
    {
        "time_step": 134,
        "datacenter_id": "DC4",
        "server_generation": "CPU.S4",
        "server_id": "8",
        "action": "buy",
        "quantity": 172
    },
    {
        "time_step": 18,
        "datacenter_id": "DC1",
        "server_generation": "CPU.S1",
        "server_id": "9",
        "action": "buy",
        "quantity": 1331
    },
    {
        "time_step": 80,
        "datacenter_id": "DC4",
        "server_generation": "CPU.S2",
        "server_id": "10",
        "action": "buy",
        "quantity": 390
    },
    {
        "time_step": 161,
        "datacenter_id": "DC4",
        "server_generation": "GPU.S3",
        "server_id": "11",
        "action": "buy",
        "quantity": 66
    },
    {
        "time_step": 14,
        "datacenter_id": "DC4",
        "server_generation": "GPU.S1",
        "server_id": "12",
        "action": "buy",
        "quantity": 89
    },
    {
        "time_step": 141,
        "datacenter_id": "DC4",
        "server_generation": "CPU.S4",
        "server_id": "17",
        "action": "buy",
        "quantity": 110
    },
    {
        "time_step": 74,
        "datacenter_id": "DC2",
        "server_generation": "GPU.S2",
        "server_id": "19",
        "action": "buy",
        "quantity": 166
    },
    {
        "time_step": 6,
        "datacenter_id": "DC4",
        "server_generation": "GPU.S1",
        "server_id": "20",
        "action": "buy",
        "quantity": 21
    },
    {
        "time_step": 164,
        "datacenter_id": "DC1",
        "server_generation": "CPU.S4",
        "server_id": "21",
        "action": "buy",
        "quantity": 59
    },
    {
        "time_step": 10,
        "datacenter_id": "DC4",
        "server_generation": "CPU.S1",
        "server_id": "22",
        "action": "buy",
        "quantity": 359
    },
    {
        "time_step": 143,
        "datacenter_id": "DC3",
        "server_generation": "CPU.S4",
        "server_id": "23",
        "action": "buy",
        "quantity": 426
    },
    {
        "time_step": 149,
        "datacenter_id": "DC2",
        "server_generation": "CPU.S4",
        "server_id": "25",
        "action": "buy",
        "quantity": 360
    },
    {
        "time_step": 34,
        "datacenter_id": "DC4",
        "server_generation": "CPU.S1",
        "server_id": "26",
        "action": "buy",
        "quantity": 40
    },
    {
        "time_step": 41,
        "datacenter_id": "DC4",
        "server_generation": "CPU.S2",
        "server_id": "27",
        "action": "buy",
        "quantity": 82
    },
    {
        "time_step": 36,
        "datacenter_id": "DC2",
        "server_generation": "CPU.S1",
        "server_id": "28",
        "action": "buy",
        "quantity": 369
    },
    {
        "time_step": 152,
        "datacenter_id": "DC2",
        "server_generation": "GPU.S3",
        "server_id": "29",
        "action": "buy",
        "quantity": 380
    },
    {
        "time_step": 20,
        "datacenter_id": "DC3",
        "server_generation": "GPU.S1",
        "server_id": "30",
        "action": "buy",
        "quantity": 119
    },
    {
        "time_step": 20,
        "datacenter_id": "DC4",
        "server_generation": "CPU.S1",
        "server_id": "31",
        "action": "buy",
        "quantity": 191
    },
    {
        "time_step": 154,
        "datacenter_id": "DC1",
        "server_generation": "GPU.S3",
        "server_id": "33",
        "action": "buy",
        "quantity": 230
    },
    {
        "time_step": 152,
        "datacenter_id": "DC1",
        "server_generation": "CPU.S4",
        "server_id": "35",
        "action": "buy",
        "quantity": 148
    },
    {
        "time_step": 69,
        "datacenter_id": "DC1",
        "server_generation": "CPU.S2",
        "server_id": "36",
        "action": "buy",
        "quantity": 1236
    },
    {
        "time_step": 121,
        "datacenter_id": "DC4",
        "server_generation": "GPU.S3",
        "server_id": "37",
        "action": "buy",
        "quantity": 37
    },
    {
        "time_step": 136,
        "datacenter_id": "DC1",
        "server_generation": "CPU.S4",
        "server_id": "38",
        "action": "buy",
        "quantity": 32
    },
    {
        "time_step": 107,
        "datacenter_id": "DC1",
        "server_generation": "GPU.S3",
        "server_id": "40",
        "action": "buy",
        "quantity": 25
    },
    {
        "time_step": 141,
        "datacenter_id": "DC3",
        "server_generation": "CPU.S4",
        "server_id": "41",
        "action": "buy",
        "quantity": 336
    },
    {
        "time_step": 130,
        "datacenter_id": "DC2",
        "server_generation": "GPU.S3",
        "server_id": "42",
        "action": "buy",
        "quantity": 213
    },
    {
        "time_step": 85,
        "datacenter_id": "DC4",
        "server_generation": "GPU.S2",
        "server_id": "43",
        "action": "buy",
        "quantity": 48
    },
    {
        "time_step": 108,
        "datacenter_id": "DC2",
        "server_generation": "GPU.S3",
        "server_id": "44",
        "action": "buy",
        "quantity": 165
    },
    {
        "time_step": 113,
        "datacenter_id": "DC4",
        "server_generation": "GPU.S2",
        "server_id": "45",
        "action": "buy",
        "quantity": 22
    },
    {
        "time_step": 99,
        "datacenter_id": "DC4",
        "server_generation": "GPU.S3",
        "server_id": "46",
        "action": "buy",
        "quantity": 60
    },
    {
        "time_step": 9,
        "datacenter_id": "DC2",
        "server_generation": "GPU.S1",
        "server_id": "47",
        "action": "buy",
        "quantity": 315
    },
    {
        "time_step": 115,
        "datacenter_id": "DC1",
        "server_generation": "CPU.S4",
        "server_id": "48",
        "action": "buy",
        "quantity": 833
    },
    {
        "time_step": 148,
        "datacenter_id": "DC2",
        "server_generation": "GPU.S3",
        "server_id": "50",
        "action": "buy",
        "quantity": 45
    },
    {
        "time_step": 78,
        "datacenter_id": "DC2",
        "server_generation": "CPU.S3",
        "server_id": "51",
        "action": "buy",
        "quantity": 481
    },
    {
        "time_step": 8,
        "datacenter_id": "DC4",
        "server_generation": "CPU.S1",
        "server_id": "54",
        "action": "buy",
        "quantity": 210
    },
    {
        "time_step": 9,
        "datacenter_id": "DC4",
        "server_generation": "GPU.S1",
        "server_id": "56",
        "action": "buy",
        "quantity": 114
    },
    {
        "time_step": 23,
        "datacenter_id": "DC3",
        "server_generation": "GPU.S1",
        "server_id": "57",
        "action": "buy",
        "quantity": 31
    },
    {
        "time_step": 99,
        "datacenter_id": "DC3",
        "server_generation": "GPU.S3",
        "server_id": "58",
        "action": "buy",
        "quantity": 79
    },
    {
        "time_step": 10,
        "datacenter_id": "DC2",
        "server_generation": "CPU.S1",
        "server_id": "60",
        "action": "buy",
        "quantity": 512
    },
    {
        "time_step": 144,
        "datacenter_id": "DC3",
        "server_generation": "CPU.S4",
        "server_id": "63",
        "action": "buy",
        "quantity": 223
    },
    {
        "time_step": 19,
        "datacenter_id": "DC3",
        "server_generation": "GPU.S1",
        "server_id": "68",
        "action": "buy",
        "quantity": 18
    },
    {
        "time_step": 4,
        "datacenter_id": "DC3",
        "server_generation": "GPU.S1",
        "server_id": "69",
        "action": "buy",
        "quantity": 180
    },
    {
        "time_step": 128,
        "datacenter_id": "DC2",
        "server_generation": "CPU.S4",
        "server_id": "70",
        "action": "buy",
        "quantity": 142
    },
    {
        "time_step": 131,
        "datacenter_id": "DC2",
        "server_generation": "CPU.S4",
        "server_id": "71",
        "action": "buy",
        "quantity": 233
    },
    {
        "time_step": 80,
        "datacenter_id": "DC4",
        "server_generation": "CPU.S3",
        "server_id": "72",
        "action": "buy",
        "quantity": 77
    },
    {
        "time_step": 43,
        "datacenter_id": "DC1",
        "server_generation": "CPU.S2",
        "server_id": "74",
        "action": "buy",
        "quantity": 928
    },
    {
        "time_step": 129,
        "datacenter_id": "DC4",
        "server_generation": "CPU.S4",
        "server_id": "75",
        "action": "buy",
        "quantity": 170
    },
    {
        "time_step": 118,
        "datacenter_id": "DC2",
        "server_generation": "CPU.S4",
        "server_id": "77",
        "action": "buy",
        "quantity": 243
    },
    {
        "time_step": 31,
        "datacenter_id": "DC4",
        "server_generation": "CPU.S1",
        "server_id": "78",
        "action": "buy",
        "quantity": 179
    },
    {
        "time_step": 20,
        "datacenter_id": "DC2",
        "server_generation": "CPU.S1",
        "server_id": "79",
        "action": "buy",
        "quantity": 277
    },
    {
        "time_step": 13,
        "datacenter_id": "DC3",
        "server_generation": "CPU.S1",
        "server_id": "81",
        "action": "buy",
        "quantity": 327
    },
    {
        "time_step": 91,
        "datacenter_id": "DC4",
        "server_generation": "CPU.S3",
        "server_id": "82",
        "action": "buy",
        "quantity": 183
    },
    {
        "time_step": 88,
        "datacenter_id": "DC3",
        "server_generation": "CPU.S2",
        "server_id": "84",
        "action": "buy",
        "quantity": 235
    },
    {
        "time_step": 75,
        "datacenter_id": "DC3",
        "server_generation": "CPU.S3",
        "server_id": "85",
        "action": "buy",
        "quantity": 5
    },
    {
        "time_step": 106,
        "datacenter_id": "DC3",
        "server_generation": "GPU.S3",
        "server_id": "87",
        "action": "buy",
        "quantity": 75
    },
    {
        "time_step": 7,
        "datacenter_id": "DC1",
        "server_generation": "CPU.S1",
        "server_id": "88",
        "action": "buy",
        "quantity": 943
    },
    {
        "time_step": 12,
        "datacenter_id": "DC3",
        "server_generation": "CPU.S1",
        "server_id": "89",
        "action": "buy",
        "quantity": 110
    },
    {
        "time_step": 130,
        "datacenter_id": "DC2",
        "server_generation": "CPU.S4",
        "server_id": "92",
        "action": "buy",
        "quantity": 95
    },
    {
        "time_step": 21,
        "datacenter_id": "DC2",
        "server_generation": "CPU.S1",
        "server_id": "96",
        "action": "buy",
        "quantity": 416
    },
    {
        "time_step": 56,
        "datacenter_id": "DC3",
        "server_generation": "CPU.S2",
        "server_id": "97",
        "action": "buy",
        "quantity": 179
    },
    {
        "time_step": 122,
        "datacenter_id": "DC1",
        "server_generation": "CPU.S4",
        "server_id": "98",
        "action": "buy",
        "quantity": 48
    },
    {
        "time_step": 36,
        "datacenter_id": "DC2",
        "server_generation": "CPU.S1",
        "server_id": "102",
        "action": "buy",
        "quantity": 182
    },
    {
        "time_step": 44,
        "datacenter_id": "DC4",
        "server_generation": "CPU.S2",
        "server_id": "103",
        "action": "buy",
        "quantity": 42
    },
    {
        "time_step": 95,
        "datacenter_id": "DC3",
        "server_generation": "CPU.S3",
        "server_id": "106",
        "action": "buy",
        "quantity": 120
    },
    {
        "time_step": 12,
        "datacenter_id": "DC1",
        "server_generation": "CPU.S1",
        "server_id": "107",
        "action": "buy",
        "quantity": 186
    },
    {
        "time_step": 19,
        "datacenter_id": "DC3",
        "server_generation": "CPU.S1",
        "server_id": "109",
        "action": "buy",
        "quantity": 60
    },
    {
        "time_step": 7,
        "datacenter_id": "DC4",
        "server_generation": "CPU.S1",
        "server_id": "110",
        "action": "buy",
        "quantity": 90
    },
    {
        "time_step": 41,
        "datacenter_id": "DC2",
        "server_generation": "CPU.S2",
        "server_id": "111",
        "action": "buy",
        "quantity": 13
    },
    {
        "time_step": 36,
        "datacenter_id": "DC3",
        "server_generation": "CPU.S1",
        "server_id": "112",
        "action": "buy",
        "quantity": 10
    },
    {
        "time_step": 13,
        "datacenter_id": "DC2",
        "server_generation": "CPU.S1",
        "server_id": "113",
        "action": "buy",
        "quantity": 39
    },
    {
        "time_step": 35,
        "datacenter_id": "DC3",
        "server_generation": "CPU.S1",
        "server_id": "114",
        "action": "buy",
        "quantity": 12
    },
    {
        "time_step": 117,
        "datacenter_id": "DC3",
        "server_generation": "CPU.S4",
        "server_id": "116",
        "action": "buy",
        "quantity": 97
    },
    {
        "time_step": 51,
        "datacenter_id": "DC4",
        "server_generation": "CPU.S2",
        "server_id": "117",
        "action": "buy",
        "quantity": 115
    },
    {
        "time_step": 43,
        "datacenter_id": "DC4",
        "server_generation": "CPU.S2",
        "server_id": "120",
        "action": "buy",
        "quantity": 51
    },
    {
        "time_step": 38,
        "datacenter_id": "DC4",
        "server_generation": "CPU.S2",
        "server_id": "122",
        "action": "buy",
        "quantity": 37
    },
    {
        "time_step": 168,
        "datacenter_id": "DC3",
        "server_generation": "GPU.S3",
        "server_id": "123",
        "action": "buy",
        "quantity": 12
    },
    {
        "time_step": 26,
        "datacenter_id": "DC2",
        "server_generation": "CPU.S1",
        "server_id": "125",
        "action": "buy",
        "quantity": 190
    },
    {
        "time_step": 111,
        "datacenter_id": "DC3",
        "server_generation": "CPU.S3",
        "server_id": "127",
        "action": "buy",
        "quantity": 21
    },
    {
        "time_step": 17,
        "datacenter_id": "DC3",
        "server_generation": "GPU.S1",
        "server_id": "129",
        "action": "buy",
        "quantity": 10
    },
    {
        "time_step": 20,
        "datacenter_id": "DC4",
        "server_generation": "CPU.S1",
        "server_id": "136",
        "action": "buy",
        "quantity": 11
    },
    {
        "time_step": 8,
        "datacenter_id": "DC3",
        "server_generation": "GPU.S1",
        "server_id": "138",
        "action": "buy",
        "quantity": 67
    },
    {
        "time_step": 17,
        "datacenter_id": "DC2",
        "server_generation": "CPU.S1",
        "server_id": "141",
        "action": "buy",
        "quantity": 426
    },
    {
        "time_step": 51,
        "datacenter_id": "DC1",
        "server_generation": "GPU.S2",
        "server_id": "142",
        "action": "buy",
        "quantity": 99
    },
    {
        "time_step": 6,
        "datacenter_id": "DC1",
        "server_generation": "CPU.S1",
        "server_id": "145",
        "action": "buy",
        "quantity": 143
    },
    {
        "time_step": 119,
        "datacenter_id": "DC4",
        "server_generation": "GPU.S3",
        "server_id": "146",
        "action": "buy",
        "quantity": 16
    },
    {
        "time_step": 109,
        "datacenter_id": "DC1",
        "server_generation": "GPU.S3",
        "server_id": "149",
        "action": "buy",
        "quantity": 344
    },
    {
        "time_step": 114,
        "datacenter_id": "DC3",
        "server_generation": "CPU.S4",
        "server_id": "153",
        "action": "buy",
        "quantity": 38
    },
    {
        "time_step": 86,
        "datacenter_id": "DC4",
        "server_generation": "CPU.S3",
        "server_id": "154",
        "action": "buy",
        "quantity": 25
    },
    {
        "time_step": 9,
        "datacenter_id": "DC3",
        "server_generation": "GPU.S1",
        "server_id": "160",
        "action": "buy",
        "quantity": 19
    },
    {
        "time_step": 5,
        "datacenter_id": "DC4",
        "server_generation": "CPU.S1",
        "server_id": "166",
        "action": "buy",
        "quantity": 103
    },
    {
        "time_step": 134,
        "datacenter_id": "DC4",
        "server_generation": "CPU.S4",
        "server_id": "167",
        "action": "buy",
        "quantity": 177
    },
    {
        "time_step": 139,
        "datacenter_id": "DC4",
        "server_generation": "CPU.S4",
        "server_id": "169",
        "action": "buy",
        "quantity": 181
    },
    {
        "time_step": 31,
        "datacenter_id": "DC2",
        "server_generation": "CPU.S1",
        "server_id": "170",
        "action": "buy",
        "quantity": 422
    },
    {
        "time_step": 148,
        "datacenter_id": "DC3",
        "server_generation": "CPU.S4",
        "server_id": "177",
        "action": "buy",
        "quantity": 40
    },
    {
        "time_step": 158,
        "datacenter_id": "DC4",
        "server_generation": "CPU.S4",
        "server_id": "184",
        "action": "buy",
        "quantity": 78
    },
    {
        "time_step": 4,
        "datacenter_id": "DC4",
        "server_generation": "CPU.S1",
        "server_id": "186",
        "action": "buy",
        "quantity": 48
    },
    {
        "time_step": 22,
        "datacenter_id": "DC1",
        "server_generation": "CPU.S1",
        "server_id": "187",
        "action": "buy",
        "quantity": 634
    },
    {
        "time_step": 26,
        "datacenter_id": "DC4",
        "server_generation": "CPU.S1",
        "server_id": "188",
        "action": "buy",
        "quantity": 27
    },
    {
        "time_step": 7,
        "datacenter_id": "DC4",
        "server_generation": "CPU.S1",
        "server_id": "190",
        "action": "buy",
        "quantity": 3
    },
    {
        "time_step": 101,
        "datacenter_id": "DC2",
        "server_generation": "GPU.S3",
        "server_id": "191",
        "action": "buy",
        "quantity": 3
    },
    {
        "time_step": 14,
        "datacenter_id": "DC2",
        "server_generation": "CPU.S1",
        "server_id": "194",
        "action": "buy",
        "quantity": 295
    },
    {
        "time_step": 145,
        "datacenter_id": "DC3",
        "server_generation": "CPU.S4",
        "server_id": "198",
        "action": "buy",
        "quantity": 67
    },
    {
        "time_step": 36,
        "datacenter_id": "DC4",
        "server_generation": "CPU.S1",
        "server_id": "204",
        "action": "buy",
        "quantity": 74
    },
    {
        "time_step": 149,
        "datacenter_id": "DC4",
        "server_generation": "CPU.S4",
        "server_id": "205",
        "action": "buy",
        "quantity": 38
    },
    {
        "time_step": 146,
        "datacenter_id": "DC3",
        "server_generation": "CPU.S4",
        "server_id": "210",
        "action": "buy",
        "quantity": 18
    },
    {
        "time_step": 139,
        "datacenter_id": "DC2",
        "server_generation": "CPU.S4",
        "server_id": "213",
        "action": "buy",
        "quantity": 33
    },
    {
        "time_step": 144,
        "datacenter_id": "DC3",
        "server_generation": "CPU.S4",
        "server_id": "214",
        "action": "buy",
        "quantity": 122
    },
    {
        "time_step": 2,
        "datacenter_id": "DC4",
        "server_generation": "CPU.S1",
        "server_id": "215",
        "action": "buy",
        "quantity": 76
    },
    {
        "time_step": 97,
        "datacenter_id": "DC1",
        "server_generation": "CPU.S3",
        "server_id": "216",
        "action": "buy",
        "quantity": 717
    },
    {
        "time_step": 10,
        "datacenter_id": "DC1",
        "server_generation": "CPU.S1",
        "server_id": "219",
        "action": "buy",
        "quantity": 61
    },
    {
        "time_step": 61,
        "datacenter_id": "DC2",
        "server_generation": "CPU.S2",
        "server_id": "221",
        "action": "buy",
        "quantity": 188
    },
    {
        "time_step": 24,
        "datacenter_id": "DC1",
        "server_generation": "CPU.S1",
        "server_id": "223",
        "action": "buy",
        "quantity": 77
    },
    {
        "time_step": 8,
        "datacenter_id": "DC2",
        "server_generation": "CPU.S1",
        "server_id": "224",
        "action": "buy",
        "quantity": 192
    },
    {
        "time_step": 112,
        "datacenter_id": "DC4",
        "server_generation": "CPU.S3",
        "server_id": "228",
        "action": "buy",
        "quantity": 143
    },
    {
        "time_step": 98,
        "datacenter_id": "DC3",
        "server_generation": "GPU.S2",
        "server_id": "230",
        "action": "buy",
        "quantity": 1
    },
    {
        "time_step": 95,
        "datacenter_id": "DC3",
        "server_generation": "CPU.S3",
        "server_id": "231",
        "action": "buy",
        "quantity": 101
    },
    {
        "time_step": 95,
        "datacenter_id": "DC1",
        "server_generation": "CPU.S3",
        "server_id": "233",
        "action": "buy",
        "quantity": 50
    },
    {
        "time_step": 89,
        "datacenter_id": "DC3",
        "server_generation": "CPU.S3",
        "server_id": "243",
        "action": "buy",
        "quantity": 37
    },
    {
        "time_step": 83,
        "datacenter_id": "DC1",
        "server_generation": "CPU.S2",
        "server_id": "249",
        "action": "buy",
        "quantity": 639
    },
    {
        "time_step": 78,
        "datacenter_id": "DC1",
        "server_generation": "CPU.S3",
        "server_id": "257",
        "action": "buy",
        "quantity": 155
    },
    {
        "time_step": 43,
        "datacenter_id": "DC4",
        "server_generation": "CPU.S2",
        "server_id": "267",
        "action": "buy",
        "quantity": 75
    },
    {
        "time_step": 48,
        "datacenter_id": "DC1",
        "server_generation": "CPU.S2",
        "server_id": "269",
        "action": "buy",
        "quantity": 544
    },
    {
        "time_step": 140,
        "datacenter_id": "DC4",
        "server_generation": "CPU.S4",
        "server_id": "271",
        "action": "buy",
        "quantity": 139
    },
    {
        "time_step": 28,
        "datacenter_id": "DC4",
        "server_generation": "CPU.S1",
        "server_id": "278",
        "action": "buy",
        "quantity": 54
    },
    {
        "time_step": 156,
        "datacenter_id": "DC2",
        "server_generation": "GPU.S3",
        "server_id": "280",
        "action": "buy",
        "quantity": 1
    },
    {
        "time_step": 73,
        "datacenter_id": "DC1",
        "server_generation": "CPU.S3",
        "server_id": "283",
        "action": "buy",
        "quantity": 253
    },
    {
        "time_step": 162,
        "datacenter_id": "DC2",
        "server_generation": "CPU.S4",
        "server_id": "284",
        "action": "buy",
        "quantity": 19
    },
    {
        "time_step": 15,
        "datacenter_id": "DC4",
        "server_generation": "CPU.S1",
        "server_id": "285",
        "action": "buy",
        "quantity": 9
    },
    {
        "time_step": 51,
        "datacenter_id": "DC3",
        "server_generation": "CPU.S2",
        "server_id": "286",
        "action": "buy",
        "quantity": 7
    },
    {
        "time_step": 85,
        "datacenter_id": "DC4",
        "server_generation": "CPU.S3",
        "server_id": "288",
        "action": "buy",
        "quantity": 70
    },
    {
        "time_step": 54,
        "datacenter_id": "DC4",
        "server_generation": "CPU.S2",
        "server_id": "290",
        "action": "buy",
        "quantity": 16
    },
    {
        "time_step": 47,
        "datacenter_id": "DC4",
        "server_generation": "CPU.S2",
        "server_id": "291",
        "action": "buy",
        "quantity": 6
    },
    {
        "time_step": 33,
        "datacenter_id": "DC4",
        "server_generation": "CPU.S1",
        "server_id": "292",
        "action": "buy",
        "quantity": 41
    },
    {
        "time_step": 56,
        "datacenter_id": "DC2",
        "server_generation": "CPU.S2",
        "server_id": "294",
        "action": "buy",
        "quantity": 79
    },
    {
        "time_step": 164,
        "datacenter_id": "DC4",
        "server_generation": "CPU.S4",
        "server_id": "299",
        "action": "buy",
        "quantity": 30
    },
    {
        "time_step": 95,
        "datacenter_id": "DC2",
        "server_generation": "CPU.S3",
        "server_id": "302",
        "action": "buy",
        "quantity": 12
    },
    {
        "time_step": 130,
        "datacenter_id": "DC4",
        "server_generation": "CPU.S4",
        "server_id": "303",
        "action": "buy",
        "quantity": 36
    },
    {
        "time_step": 151,
        "datacenter_id": "DC4",
        "server_generation": "CPU.S4",
        "server_id": "304",
        "action": "buy",
        "quantity": 16
    },
    {
        "time_step": 125,
        "datacenter_id": "DC4",
        "server_generation": "CPU.S4",
        "server_id": "306",
        "action": "buy",
        "quantity": 111
    },
    {
        "time_step": 5,
        "datacenter_id": "DC1",
        "server_generation": "CPU.S1",
        "server_id": "308",
        "action": "buy",
        "quantity": 181
    },
    {
        "time_step": 124,
        "datacenter_id": "DC3",
        "server_generation": "CPU.S4",
        "server_id": "311",
        "action": "buy",
        "quantity": 5
    },
    {
        "time_step": 95,
        "datacenter_id": "DC1",
        "server_generation": "CPU.S2",
        "server_id": "320",
        "action": "buy",
        "quantity": 67
    },
    {
        "time_step": 38,
        "datacenter_id": "DC4",
        "server_generation": "CPU.S2",
        "server_id": "324",
        "action": "buy",
        "quantity": 36
    },
    {
        "time_step": 113,
        "datacenter_id": "DC2",
        "server_generation": "GPU.S3",
        "server_id": "326",
        "action": "buy",
        "quantity": 2
    },
    {
        "time_step": 40,
        "datacenter_id": "DC2",
        "server_generation": "CPU.S2",
        "server_id": "329",
        "action": "buy",
        "quantity": 190
    },
    {
        "time_step": 121,
        "datacenter_id": "DC4",
        "server_generation": "CPU.S4",
        "server_id": "333",
        "action": "buy",
        "quantity": 4
    },
    {
        "time_step": 46,
        "datacenter_id": "DC4",
        "server_generation": "CPU.S2",
        "server_id": "338",
        "action": "buy",
        "quantity": 28
    },
    {
        "time_step": 44,
        "datacenter_id": "DC2",
        "server_generation": "CPU.S2",
        "server_id": "342",
        "action": "buy",
        "quantity": 23
    },
    {
        "time_step": 79,
        "datacenter_id": "DC4",
        "server_generation": "CPU.S3",
        "server_id": "346",
        "action": "buy",
        "quantity": 47
    },
    {
        "time_step": 41,
        "datacenter_id": "DC1",
        "server_generation": "CPU.S2",
        "server_id": "347",
        "action": "buy",
        "quantity": 396
    },
    {
        "time_step": 17,
        "datacenter_id": "DC4",
        "server_generation": "CPU.S1",
        "server_id": "356",
        "action": "buy",
        "quantity": 44
    },
    {
        "time_step": 42,
        "datacenter_id": "DC3",
        "server_generation": "CPU.S2",
        "server_id": "358",
        "action": "buy",
        "quantity": 140
    },
    {
        "time_step": 13,
        "datacenter_id": "DC3",
        "server_generation": "CPU.S1",
        "server_id": "363",
        "action": "buy",
        "quantity": 47
    },
    {
        "time_step": 129,
        "datacenter_id": "DC2",
        "server_generation": "CPU.S4",
        "server_id": "364",
        "action": "buy",
        "quantity": 175
    },
    {
        "time_step": 130,
        "datacenter_id": "DC1",
        "server_generation": "CPU.S4",
        "server_id": "365",
        "action": "buy",
        "quantity": 46
    },
    {
        "time_step": 10,
        "datacenter_id": "DC2",
        "server_generation": "CPU.S1",
        "server_id": "368",
        "action": "buy",
        "quantity": 88
    },
    {
        "time_step": 23,
        "datacenter_id": "DC4",
        "server_generation": "GPU.S1",
        "server_id": "369",
        "action": "buy",
        "quantity": 5
    },
    {
        "time_step": 4,
        "datacenter_id": "DC3",
        "server_generation": "GPU.S1",
        "server_id": "374",
        "action": "buy",
        "quantity": 6
    },
    {
        "time_step": 153,
        "datacenter_id": "DC3",
        "server_generation": "CPU.S4",
        "server_id": "378",
        "action": "buy",
        "quantity": 115
    },
    {
        "time_step": 21,
        "datacenter_id": "DC2",
        "server_generation": "CPU.S1",
        "server_id": "396",
        "action": "buy",
        "quantity": 135
    },
    {
        "time_step": 74,
        "datacenter_id": "DC3",
        "server_generation": "CPU.S2",
        "server_id": "408",
        "action": "buy",
        "quantity": 87
    },
    {
        "time_step": 69,
        "datacenter_id": "DC3",
        "server_generation": "CPU.S2",
        "server_id": "410",
        "action": "buy",
        "quantity": 9
    },
    {
        "time_step": 41,
        "datacenter_id": "DC4",
        "server_generation": "CPU.S2",
        "server_id": "412",
        "action": "buy",
        "quantity": 4
    },
    {
        "time_step": 99,
        "datacenter_id": "DC4",
        "server_generation": "CPU.S3",
        "server_id": "433",
        "action": "buy",
        "quantity": 12
    },
    {
        "time_step": 156,
        "datacenter_id": "DC3",
        "server_generation": "CPU.S4",
        "server_id": "436",
        "action": "buy",
        "quantity": 10
    },
    {
        "time_step": 116,
        "datacenter_id": "DC4",
        "server_generation": "GPU.S3",
        "server_id": "445",
        "action": "buy",
        "quantity": 1
    },
    {
        "time_step": 64,
        "datacenter_id": "DC1",
        "server_generation": "CPU.S2",
        "server_id": "449",
        "action": "buy",
        "quantity": 99
    },
    {
        "time_step": 61,
        "datacenter_id": "DC3",
        "server_generation": "CPU.S2",
        "server_id": "451",
        "action": "buy",
        "quantity": 39
    },
    {
        "time_step": 61,
        "datacenter_id": "DC4",
        "server_generation": "CPU.S2",
        "server_id": "453",
        "action": "buy",
        "quantity": 7
    },
    {
        "time_step": 107,
        "datacenter_id": "DC1",
        "server_generation": "GPU.S2",
        "server_id": "454",
        "action": "buy",
        "quantity": 13
    },
    {
        "time_step": 46,
        "datacenter_id": "DC2",
        "server_generation": "CPU.S2",
        "server_id": "456",
        "action": "buy",
        "quantity": 140
    },
    {
        "time_step": 133,
        "datacenter_id": "DC4",
        "server_generation": "GPU.S3",
        "server_id": "463",
        "action": "buy",
        "quantity": 1
    },
    {
        "time_step": 158,
        "datacenter_id": "DC4",
        "server_generation": "CPU.S4",
        "server_id": "473",
        "action": "buy",
        "quantity": 18
    },
    {
        "time_step": 52,
        "datacenter_id": "DC4",
        "server_generation": "GPU.S2",
        "server_id": "482",
        "action": "buy",
        "quantity": 3
    },
    {
        "time_step": 123,
        "datacenter_id": "DC4",
        "server_generation": "CPU.S4",
        "server_id": "489",
        "action": "buy",
        "quantity": 6
    },
    {
        "time_step": 125,
        "datacenter_id": "DC4",
        "server_generation": "CPU.S4",
        "server_id": "491",
        "action": "buy",
        "quantity": 21
    },
    {
        "time_step": 38,
        "datacenter_id": "DC4",
        "server_generation": "CPU.S2",
        "server_id": "492",
        "action": "buy",
        "quantity": 24
    },
    {
        "time_step": 14,
        "datacenter_id": "DC4",
        "server_generation": "CPU.S1",
        "server_id": "495",
        "action": "buy",
        "quantity": 43
    },
    {
        "time_step": 70,
        "datacenter_id": "DC3",
        "server_generation": "CPU.S2",
        "server_id": "499",
        "action": "buy",
        "quantity": 57
    },
    {
        "time_step": 47,
        "datacenter_id": "DC1",
        "server_generation": "CPU.S2",
        "server_id": "500",
        "action": "buy",
        "quantity": 187
    }
]